pygame_colliders/__init__.py
pygame_colliders/base.py
pygame_colliders/concave.py
pygame_colliders/convex.py
pygame_colliders/rect.py
pygame_colliders/utils.py
pygame_colliders/vector.py
pygame_colliders-0.1.4.dist-info/LICENSE
pygame_colliders-0.1.4.dist-info/WHEEL
pygame_colliders-0.1.4.dist-info/METADATA
pygame_colliders-0.1.4.dist-info/RECORD
